code/hdl/spi_verilog.v
// @title      SPI protocol specific for Intan RHS, multi MISO/MOSI
// @category   interface
// @file       spi_verilog.v
// @author     Mattia Di Florio
// @date       07 jun 2024
// @version    0.1
// @copyright
// © 2024 Mattia Di Florio <di.florio.mattia@gmail.com>
// SPDX-License-Identifier: MIT License
//
// @brief
// SPI protocol specific for Intan RHS2116 chip, CPOL = 0, CPHA = 0.
// For more info, refer to Intan RHS2116 Datasheet
// 
// @changelog
// > 
///////////////////////////////////////////////////////////////////////////////

module spi_verilog
#( parameter CLK_FREQ    = 100000000,                   // main clk default values
   parameter WORD_LENGTH =        32,                   // length of data for TX and RX
   parameter SPICLK_FREQ =  25000000                    // spi clk default value
)

( input wire clk,                                       // main clock
  input wire reset,                                     // reset signal
  output wire cs,                                       // chip select

  output reg  mosi_1,                                   // master out slave in output 1
  input  wire miso_1,                                   // master in slave out input 1
  output reg  mosi_2,                                   // master out slave in output 2
  input  wire miso_2,                                   // master in slave out input 1

  output wire sclk,                                     // SPI clock

  //interface
  input  wire data_in_v,                                // master in slave out input 1
  output wire ready_out,                                // ready to get new data to transmit
  output wire data_out_v,                               // data received validity, new data available flag

  input  wire [WORD_LENGTH-1:0] data_in_1,              // data to transmit over mosi_1
  input  wire [WORD_LENGTH-1:0] data_in_2,              // data to transmit over mosi_2

  output reg [WORD_LENGTH-1:0] data_out_1,              // data received from miso_1
  output reg [WORD_LENGTH-1:0] data_out_2               // data received from miso_2

);



parameter TCSOFF = 10;                                  // to guarantee at least a CS off time of 100 ns

// SPI clock state machine
parameter zero = 1'b0;                                  
parameter one  = 1'b1;                                  
reg     clk_controller;                                 

reg     clk_trig;                                       // trigger sclk
integer clk_inc;                                        // counter for sclk generation

// main state machine for data TX and RX
parameter idle    = 2'b00;                              
parameter start   = 2'b01;                              
parameter wait_cs = 2'b10;                              
reg [1:0] main_proc;                                    

integer   clk_counter;                                  // counter for data transmission/reception
integer   cs_counter = 0;                               // counter for tcsoff
reg       go_proc;                                      
reg       chip_sel;                                     // chip select
reg       busy_flag;                                    // SPI module busy flag
reg       data_ready;                                   // new data available flag

reg [WORD_LENGTH-1:0] shift_reg_tx_1;                   // shift register transmitter 
reg [WORD_LENGTH-1:0] shift_reg_tx_2;                   // shift register transmitter 
reg [WORD_LENGTH-1:0] shift_reg_rx_1;                   // shift register receiver 
reg [WORD_LENGTH-1:0] shift_reg_rx_2;                   //shift register receiver 



// SPI clock (sclk) generation
always @(posedge(clk)) begin: clk_generation
    if (reset == 1'b1) begin
        clk_controller <= zero;
        clk_trig       <= 1'b0;
        clk_inc        <= 0;
        
    end else begin
        case(clk_controller)
            zero: begin
                if (clk_inc < ((CLK_FREQ/(SPICLK_FREQ))/2)) begin
                    clk_inc <= clk_inc + 1;

                    if (clk_inc == ((CLK_FREQ/(SPICLK_FREQ))/2) - 1) begin
                        clk_controller <= one;
                        clk_trig <= 1'b0;
                    
                    end else begin
                        clk_trig <= 1'b1;

                    end
                end    
                end

            one: begin
                if (clk_inc < (CLK_FREQ/(SPICLK_FREQ))) begin
                    clk_inc <= clk_inc + 1;

                    if (clk_inc == (CLK_FREQ/(SPICLK_FREQ)) - 1) begin
                        clk_inc        <= 0;
                        clk_controller <= zero;
                        clk_trig       <= 1'b1;
                    
                    end else begin
                        clk_trig <= 1'b0;

                    end
                end
            end
        endcase
    end
end


always @(posedge(clk)) begin: SPI_communication
    if (reset == 1'b1) begin
        main_proc   <= idle;
        clk_counter <=  0;
        go_proc     <= 1'b0;
        chip_sel    <= 1'b1;
        busy_flag   <= 1'b0;
        data_ready  <= 1'b1;        

    end else begin
        case(main_proc)
        idle: begin
            data_ready   <= 1'b0;                                                                                           // new data available flag                              
            if (data_in_v == 1'b1 && busy_flag == 1'b0) begin
                
                shift_reg_tx_1 <= data_in_1;                                                                                // update data to transmit  
                shift_reg_tx_2 <= data_in_2;                                                                                // update data to transmit          
                go_proc        <= 1'b1;                                                                                     // fsm state update
                busy_flag      <= 1'b1;                                                                                     // busy flag

            end else if (go_proc == 1'b1 && clk_trig == 1'b1 && clk_inc == (CLK_FREQ/(SPICLK_FREQ*2)) - 1) begin            // on the falling edge of clk_trig
                chip_sel                        <= 1'b0;                                                                    // chip select
                main_proc                       <= start;
                go_proc                         <= 1'b0;   
                clk_counter                     <= clk_counter + 1;                         
                //input 1                       
                shift_reg_tx_1[WORD_LENGTH-1:1] <= shift_reg_tx_1[WORD_LENGTH-2:0];                                     	// update bit to transmit on mosi
                mosi_1                          <= shift_reg_tx_1[WORD_LENGTH-1];                                       	// bit transmission on mosi
                shift_reg_rx_1                  <= {shift_reg_rx_1[WORD_LENGTH-2:0], miso_1};                           	// update bit to receive on miso
                //input 2                     
                shift_reg_tx_2[WORD_LENGTH-1:1] <= shift_reg_tx_2[WORD_LENGTH-2:0];                                         // update bit to transmit on mosi
                mosi_2                          <= shift_reg_tx_2[WORD_LENGTH-1];                                           // bit transmission on mosi
                shift_reg_rx_2                  <= {shift_reg_rx_2[WORD_LENGTH-2:0], miso_2};                               // update bit to receive on miso

            end else begin
                main_proc <= idle;
            end
        end


        start: begin
            if (clk_inc == ((CLK_FREQ/(SPICLK_FREQ)) - (CLK_FREQ/(SPICLK_FREQ*2))) - 1) begin                               // to guarantee cpha = 0
                if (clk_counter == WORD_LENGTH) begin                                                                       // if all the bits have been transmitted/received end communication
                    main_proc                       <= wait_cs;
                    clk_counter                     <=  0;                                                                  // count the number of bits transmitted
                    //input 1                       
                    shift_reg_tx_1[WORD_LENGTH-1:1] <= shift_reg_tx_1[WORD_LENGTH-2:0];                                     // update bit to transmit on mosi
                    mosi_1                          <= shift_reg_tx_1[WORD_LENGTH-1];                                       // bit transmission on mosi
                    shift_reg_rx_1                  <= {shift_reg_rx_1[WORD_LENGTH-2:0], miso_1};                           // update bit to receive on miso
                    //input 2                     
                    shift_reg_tx_2[WORD_LENGTH-1:1] <= shift_reg_tx_2[WORD_LENGTH-2:0];                                     // update bit to transmit on mosi
                    mosi_2                          <= shift_reg_tx_2[WORD_LENGTH-1];                                       // bit transmission on mosi
                    shift_reg_rx_2                  <= {shift_reg_rx_2[WORD_LENGTH-2:0], miso_2};                           // update bit to receive on miso

                end else begin
                    main_proc                       <= start;
                    clk_counter                     <= clk_counter + 1;                                                
                    //input 1                       
                    shift_reg_tx_1[WORD_LENGTH-1:1] <= shift_reg_tx_1[WORD_LENGTH-2:0];                                     // update bit to transmit on mosi
                    mosi_1                          <= shift_reg_tx_1[WORD_LENGTH-1];                                       // bit transmission on mosi
                    shift_reg_rx_1                  <= {shift_reg_rx_1[WORD_LENGTH-2:0], miso_1};                           // update bit to receive on miso
                    //input 2                     
                    shift_reg_tx_2[WORD_LENGTH-1:1] <= shift_reg_tx_2[WORD_LENGTH-2:0];                                     // update bit to transmit on mosi
                    mosi_2                          <= shift_reg_tx_2[WORD_LENGTH-1];                                       // bit transmission on mosi
                    shift_reg_rx_2                  <= {shift_reg_rx_2[WORD_LENGTH-2:0], miso_2};                           // update bit to receive on miso

                end;
            end;
        end

        wait_cs: begin
            if (clk_trig == 1'b0 && clk_inc == (CLK_FREQ/(SPICLK_FREQ)) - 1 && chip_sel == 1'b0) begin                      // guarantee simmetry between high/low transition of chip select
                chip_sel <= 1'b1;

            end else if (cs_counter < TCSOFF - 4 && chip_sel == 1'b1) begin                                                 // to guarantee tcsoff 
                cs_counter <= cs_counter + 1;                                                                               // increment tcsoff counter
            
            end else if (cs_counter == TCSOFF - 4 && chip_sel == 1'b1) begin                   
                cs_counter <=  0;
                busy_flag  <= 1'b0;
                main_proc  <= idle;
                data_out_1 <= shift_reg_rx_1;                                                                               // output received data
                data_out_2 <= shift_reg_rx_2;                                                                               // output received data
                data_ready <= 1'b1;                                                                                         // received data validity flag

            end;
        end
        endcase
    end
end


assign sclk       = (chip_sel == 1'b0) ? clk_trig : 1'b0;   	// output SPI clock 
assign cs         = chip_sel;                                   // output chip select
assign ready_out  = !busy_flag;                                 // SPI ready for new operation
assign data_out_v = data_ready;                                 // new data available


endmodule

code/hdl_tb/spi_verilog_tb.v
// @title      SPI protocol specific for Intan RHS, testbench
// @file       spi_verilog_tb.vhd
// @author     Mattia Di Florio
// @date       7 jun 2024
// @version    0.1
// @copyright
// © 2024 Mattia Di Florio <di.florio.mattia@gmail.com>
// SPDX-License-Identifier: MIT License
//
// @brief
// SPI protocol tb for Intan RHS devices, CPOL = 0, CPHA = 0.
// For more info, refer to Intan RHS2116 Datasheet
// 
// @changelog
// > 

`timescale 1ns/1ps
`include "/mnt/d/GitHub/SPI-master-RHS2116/code/hdl/spi_verilog.v"


module spi_verilog_tb;

    // Parameters
    localparam  CLK_FREQ    = 100000000;
    localparam  WORD_LENGTH =        32;
    localparam  SPICLK_FREQ =  25000000;

    localparam COUNTER_MAX = 1;
    localparam END_SIM = 10;

    //Ports
    reg  clk = 0;
    reg  reset;
    wire cs;
    wire mosi_1;
    wire  miso_1;
    wire mosi_2;
    wire  miso_2;
    wire sclk;
    reg  data_in_v;
    wire ready_out;
    wire data_out_v;
    reg  [WORD_LENGTH-1:0] data_in_1;
    reg  [WORD_LENGTH-1:0] data_in_2;
    wire [WORD_LENGTH-1:0] data_out_1;
    wire [WORD_LENGTH-1:0] data_out_2;

    integer x = 0;
    integer counter = 0;
    integer data = 0;


    spi_verilog # (
        .CLK_FREQ(CLK_FREQ),
        .WORD_LENGTH(WORD_LENGTH),
        .SPICLK_FREQ(SPICLK_FREQ)
    )

    spi_verilog_inst (
        .clk(clk),
        .reset(reset),
        .cs(cs),
        .mosi_1(mosi_1),
        .miso_1(miso_1),
        .mosi_2(mosi_2),
        .miso_2(miso_2),
        .sclk(sclk),
        .data_in_v(data_in_v),
        .ready_out(ready_out),
        .data_out_v(data_out_v),
        .data_in_1(data_in_1),
        .data_in_2(data_in_2),
        .data_out_1(data_out_1),
        .data_out_2(data_out_2)
    );

    always #5  clk = ! clk;    // 10 ns delay

    initial begin
        // for icarus verilog simulator
        $dumpfile("spi_verilog_tb.vcd");
        $dumpvars;
        reset = 1'b1;
        #30
        reset = 1'b0;
    end

    always @(posedge(clk)) begin

        if (reset) begin
            
        end else if (counter < COUNTER_MAX) begin
            counter <= counter + 1;
            data_in_v <= 1'b0;
        end else if (counter == COUNTER_MAX && data_in_v == 1'b0) begin
            data_in_1 <= data;
            data_in_2 <= data;
            data_in_v <= 1'b1;
        end else if (data_in_v == 1'b1 && ready_out == 1'b1) begin
            if (data < 150) begin
                data <= data + 1;
            end else begin
                data <= 0;
            end
            counter   <= 0;
            data_in_v <= 1'b0;

            x <= x + 1;
            #10;    
            if (x>END_SIM) begin
                $finish;
            end  
        end  
        
    end

    assign miso_1 = mosi_1;
    assign miso_2 = mosi_2;

endmodule

code/hdl_tb/spi_verilog_tb.vcd
$date
	Sat Jun  8 21:44:19 2024
$end
$version
	Icarus Verilog
$end
$timescale
	1ps
$end
$scope module spi_verilog_tb $end
$var wire 1 ! miso_1 $end
$var wire 1 " miso_2 $end
$var wire 1 # sclk $end
$var wire 1 $ ready_out $end
$var wire 1 % mosi_2 $end
$var wire 1 & mosi_1 $end
$var wire 1 ' data_out_v $end
$var wire 32 ( data_out_2 [31:0] $end
$var wire 32 ) data_out_1 [31:0] $end
$var wire 1 * cs $end
$var reg 1 + clk $end
$var reg 32 , data_in_1 [31:0] $end
$var reg 32 - data_in_2 [31:0] $end
$var reg 1 . data_in_v $end
$var reg 1 / reset $end
$var integer 32 0 counter [31:0] $end
$var integer 32 1 data [31:0] $end
$var integer 32 2 x [31:0] $end
$scope module spi_verilog_inst $end
$var wire 1 + clk $end
$var wire 1 * cs $end
$var wire 32 3 data_in_1 [31:0] $end
$var wire 32 4 data_in_2 [31:0] $end
$var wire 1 . data_in_v $end
$var wire 1 ' data_out_v $end
$var wire 1 ! miso_1 $end
$var wire 1 " miso_2 $end
$var wire 1 / reset $end
$var wire 1 # sclk $end
$var wire 1 $ ready_out $end
$var reg 1 5 busy_flag $end
$var reg 1 6 chip_sel $end
$var reg 1 7 clk_controller $end
$var reg 1 8 clk_trig $end
$var reg 32 9 data_out_1 [31:0] $end
$var reg 32 : data_out_2 [31:0] $end
$var reg 1 ; data_ready $end
$var reg 1 < go_proc $end
$var reg 2 = main_proc [1:0] $end
$var reg 1 & mosi_1 $end
$var reg 1 % mosi_2 $end
$var reg 32 > shift_reg_rx_1 [31:0] $end
$var reg 32 ? shift_reg_rx_2 [31:0] $end
$var reg 32 @ shift_reg_tx_1 [31:0] $end
$var reg 32 A shift_reg_tx_2 [31:0] $end
$var integer 32 B clk_counter [31:0] $end
$var integer 32 C clk_inc [31:0] $end
$var integer 32 D cs_counter [31:0] $end
$scope begin SPI_communication $end
$upscope $end
$scope begin clk_generation $end
$upscope $end
$upscope $end
$upscope $end
$enddefinitions $end
#0
$dumpvars
b0 D
bx C
bx B
bx A
bx @
bx ?
bx >
bx =
x<
x;
bx :
bx 9
x8
x7
x6
x5
bx 4
bx 3
b0 2
b0 1
b0 0
1/
x.
bx -
bx ,
0+
x*
bx )
bx (
x'
x&
x%
x$
x#
x"
x!
$end
#5000
0#
1'
1;
1$
05
1*
16
0<
b0 B
b0 =
b0 C
08
07
1+
#10000
0+
#15000
1+
#20000
0+
#25000
1+
#30000
0+
0/
#35000
0'
0;
18
b1 C
0.
b1 0
1+
#40000
0+
#45000
08
17
b10 C
1.
b0 -
b0 4
b0 ,
b0 3
1+
#50000
0+
#55000
0$
15
1<
b0 A
b0 @
b11 C
b1 2
0.
b0 0
b1 1
1+
#60000
0+
#65000
18
07
b0 C
b1 0
1+
#70000
0+
#75000
b1 C
1.
b1 -
b1 4
b1 ,
b1 3
1+
#80000
0+
#85000
0"
0%
0!
0&
b1 B
0<
b1 =
0*
06
08
17
b10 C
1+
#90000
0+
#95000
b11 C
1+
#100000
0+
#105000
1#
18
07
b0 C
1+
#110000
0+
#115000
b1 C
1+
#120000
0+
#125000
0#
bx0 ?
bx0 >
b10 B
08
17
b10 C
1+
#130000
0+
#135000
b11 C
1+
#140000
0+
#145000
1#
18
07
b0 C
1+
#150000
0+
#155000
b1 C
1+
#160000
0+
#165000
0#
bx00 ?
bx00 >
b11 B
08
17
b10 C
1+
#170000
0+
#175000
b11 C
1+
#180000
0+
#185000
1#
18
07
b0 C
1+
#190000
0+
#195000
b1 C
1+
#200000
0+
#205000
0#
bx000 ?
bx000 >
b100 B
08
17
b10 C
1+
#210000
0+
#215000
b11 C
1+
#220000
0+
#225000
1#
18
07
b0 C
1+
#230000
0+
#235000
b1 C
1+
#240000
0+
#245000
0#
bx0000 ?
bx0000 >
b101 B
08
17
b10 C
1+
#250000
0+
#255000
b11 C
1+
#260000
0+
#265000
1#
18
07
b0 C
1+
#270000
0+
#275000
b1 C
1+
#280000
0+
#285000
0#
bx00000 ?
bx00000 >
b110 B
08
17
b10 C
1+
#290000
0+
#295000
b11 C
1+
#300000
0+
#305000
1#
18
07
b0 C
1+
#310000
0+
#315000
b1 C
1+
#320000
0+
#325000
0#
bx000000 ?
bx000000 >
b111 B
08
17
b10 C
1+
#330000
0+
#335000
b11 C
1+
#340000
0+
#345000
1#
18
07
b0 C
1+
#350000
0+
#355000
b1 C
1+
#360000
0+
#365000
0#
bx0000000 ?
bx0000000 >
b1000 B
08
17
b10 C
1+
#370000
0+
#375000
b11 C
1+
#380000
0+
#385000
1#
18
07
b0 C
1+
#390000
0+
#395000
b1 C
1+
#400000
0+
#405000
0#
bx00000000 ?
bx00000000 >
b1001 B
08
17
b10 C
1+
#410000
0+
#415000
b11 C
1+
#420000
0+
#425000
1#
18
07
b0 C
1+
#430000
0+
#435000
b1 C
1+
#440000
0+
#445000
0#
bx000000000 ?
bx000000000 >
b1010 B
08
17
b10 C
1+
#450000
0+
#455000
b11 C
1+
#460000
0+
#465000
1#
18
07
b0 C
1+
#470000
0+
#475000
b1 C
1+
#480000
0+
#485000
0#
bx0000000000 ?
bx0000000000 >
b1011 B
08
17
b10 C
1+
#490000
0+
#495000
b11 C
1+
#500000
0+
#505000
1#
18
07
b0 C
1+
#510000
0+
#515000
b1 C
1+
#520000
0+
#525000
0#
bx00000000000 ?
bx00000000000 >
b1100 B
08
17
b10 C
1+
#530000
0+
#535000
b11 C
1+
#540000
0+
#545000
1#
18
07
b0 C
1+
#550000
0+
#555000
b1 C
1+
#560000
0+
#565000
0#
bx000000000000 ?
bx000000000000 >
b1101 B
08
17
b10 C
1+
#570000
0+
#575000
b11 C
1+
#580000
0+
#585000
1#
18
07
b0 C
1+
#590000
0+
#595000
b1 C
1+
#600000
0+
#605000
0#
bx0000000000000 ?
bx0000000000000 >
b1110 B
08
17
b10 C
1+
#610000
0+
#615000
b11 C
1+
#620000
0+
#625000
1#
18
07
b0 C
1+
#630000
0+
#635000
b1 C
1+
#640000
0+
#645000
0#
bx00000000000000 ?
bx00000000000000 >
b1111 B
08
17
b10 C
1+
#650000
0+
#655000
b11 C
1+
#660000
0+
#665000
1#
18
07
b0 C
1+
#670000
0+
#675000
b1 C
1+
#680000
0+
#685000
0#
bx000000000000000 ?
bx000000000000000 >
b10000 B
08
17
b10 C
1+
#690000
0+
#695000
b11 C
1+
#700000
0+
#705000
1#
18
07
b0 C
1+
#710000
0+
#715000
b1 C
1+
#720000
0+
#725000
0#
bx0000000000000000 ?
bx0000000000000000 >
b10001 B
08
17
b10 C
1+
#730000
0+
#735000
b11 C
1+
#740000
0+
#745000
1#
18
07
b0 C
1+
#750000
0+
#755000
b1 C
1+
#760000
0+
#765000
0#
bx00000000000000000 ?
bx00000000000000000 >
b10010 B
08
17
b10 C
1+
#770000
0+
#775000
b11 C
1+
#780000
0+
#785000
1#
18
07
b0 C
1+
#790000
0+
#795000
b1 C
1+
#800000
0+
#805000
0#
bx000000000000000000 ?
bx000000000000000000 >
b10011 B
08
17
b10 C
1+
#810000
0+
#815000
b11 C
1+
#820000
0+
#825000
1#
18
07
b0 C
1+
#830000
0+
#835000
b1 C
1+
#840000
0+
#845000
0#
bx0000000000000000000 ?
bx0000000000000000000 >
b10100 B
08
17
b10 C
1+
#850000
0+
#855000
b11 C
1+
#860000
0+
#865000
1#
18
07
b0 C
1+
#870000
0+
#875000
b1 C
1+
#880000
0+
#885000
0#
bx00000000000000000000 ?
bx00000000000000000000 >
b10101 B
08
17
b10 C
1+
#890000
0+
#895000
b11 C
1+
#900000
0+
#905000
1#
18
07
b0 C
1+
#910000
0+
#915000
b1 C
1+
#920000
0+
#925000
0#
bx000000000000000000000 ?
bx000000000000000000000 >
b10110 B
08
17
b10 C
1+
#930000
0+
#935000
b11 C
1+
#940000
0+
#945000
1#
18
07
b0 C
1+
#950000
0+
#955000
b1 C
1+
#960000
0+
#965000
0#
bx0000000000000000000000 ?
bx0000000000000000000000 >
b10111 B
08
17
b10 C
1+
#970000
0+
#975000
b11 C
1+
#980000
0+
#985000
1#
18
07
b0 C
1+
#990000
0+
#995000
b1 C
1+
#1000000
0+
#1005000
0#
bx00000000000000000000000 ?
bx00000000000000000000000 >
b11000 B
08
17
b10 C
1+
#1010000
0+
#1015000
b11 C
1+
#1020000
0+
#1025000
1#
18
07
b0 C
1+
#1030000
0+
#1035000
b1 C
1+
#1040000
0+
#1045000
0#
bx000000000000000000000000 ?
bx000000000000000000000000 >
b11001 B
08
17
b10 C
1+
#1050000
0+
#1055000
b11 C
1+
#1060000
0+
#1065000
1#
18
07
b0 C
1+
#1070000
0+
#1075000
b1 C
1+
#1080000
0+
#1085000
0#
bx0000000000000000000000000 ?
bx0000000000000000000000000 >
b11010 B
08
17
b10 C
1+
#1090000
0+
#1095000
b11 C
1+
#1100000
0+
#1105000
1#
18
07
b0 C
1+
#1110000
0+
#1115000
b1 C
1+
#1120000
0+
#1125000
0#
bx00000000000000000000000000 ?
bx00000000000000000000000000 >
b11011 B
08
17
b10 C
1+
#1130000
0+
#1135000
b11 C
1+
#1140000
0+
#1145000
1#
18
07
b0 C
1+
#1150000
0+
#1155000
b1 C
1+
#1160000
0+
#1165000
0#
bx000000000000000000000000000 ?
bx000000000000000000000000000 >
b11100 B
08
17
b10 C
1+
#1170000
0+
#1175000
b11 C
1+
#1180000
0+
#1185000
1#
18
07
b0 C
1+
#1190000
0+
#1195000
b1 C
1+
#1200000
0+
#1205000
0#
bx0000000000000000000000000000 ?
bx0000000000000000000000000000 >
b11101 B
08
17
b10 C
1+
#1210000
0+
#1215000
b11 C
1+
#1220000
0+
#1225000
1#
18
07
b0 C
1+
#1230000
0+
#1235000
b1 C
1+
#1240000
0+
#1245000
0#
bx00000000000000000000000000000 ?
bx00000000000000000000000000000 >
b11110 B
08
17
b10 C
1+
#1250000
0+
#1255000
b11 C
1+
#1260000
0+
#1265000
1#
18
07
b0 C
1+
#1270000
0+
#1275000
b1 C
1+
#1280000
0+
#1285000
0#
bx000000000000000000000000000000 ?
bx000000000000000000000000000000 >
b11111 B
08
17
b10 C
1+
#1290000
0+
#1295000
b11 C
1+
#1300000
0+
#1305000
1#
18
07
b0 C
1+
#1310000
0+
#1315000
b1 C
1+
#1320000
0+
#1325000
0#
bx0000000000000000000000000000000 ?
bx0000000000000000000000000000000 >
b100000 B
08
17
b10 C
1+
#1330000
0+
#1335000
b11 C
1+
#1340000
0+
#1345000
1#
18
07
b0 C
1+
#1350000
0+
#1355000
b1 C
1+
#1360000
0+
#1365000
0#
b0 ?
b0 >
b0 B
b10 =
08
17
b10 C
1+
#1370000
0+
#1375000
b11 C
1+
#1380000
0+
#1385000
0#
1*
16
18
07
b0 C
1+
#1390000
0+
#1395000
b1 D
b1 C
1+
#1400000
0+
#1405000
b10 D
08
17
b10 C
1+
#1410000
0+
#1415000
b11 D
b11 C
1+
#1420000
0+
#1425000
b100 D
18
07
b0 C
1+
#1430000
0+
#1435000
b101 D
b1 C
1+
#1440000
0+
#1445000
b110 D
08
17
b10 C
1+
#1450000
0+
#1455000
1'
1;
b0 (
b0 :
b0 )
b0 9
b0 =
1$
05
b0 D
b11 C
1+
#1460000
0+
#1465000
0$
15
1<
b1 A
b1 @
0'
0;
18
07
b0 C
b10 2
0.
b0 0
b10 1
1+
#1470000
0+
#1475000
b1 C
b1 0
1+
#1480000
0+
#1485000
b11 A
b11 @
b1 B
0<
b1 =
0*
06
08
17
b10 C
1.
b10 -
b10 4
b10 ,
b10 3
1+
#1490000
0+
#1495000
b11 C
1+
#1500000
0+
#1505000
1#
18
07
b0 C
1+
#1510000
0+
#1515000
b1 C
1+
#1520000
0+
#1525000
0#
b111 A
b111 @
b10 B
08
17
b10 C
1+
#1530000
0+
#1535000
b11 C
1+
#1540000
0+
#1545000
1#
18
07
b0 C
1+
#1550000
0+
#1555000
b1 C
1+
#1560000
0+
#1565000
0#
b1111 A
b1111 @
b11 B
08
17
b10 C
1+
#1570000
0+
#1575000
b11 C
1+
#1580000
0+
#1585000
1#
18
07
b0 C
1+
#1590000
0+
#1595000
b1 C
1+
#1600000
0+
#1605000
0#
b11111 A
b11111 @
b100 B
08
17
b10 C
1+
#1610000
0+
#1615000
b11 C
1+
#1620000
0+
#1625000
1#
18
07
b0 C
1+
#1630000
0+
#1635000
b1 C
1+
#1640000
0+
#1645000
0#
b111111 A
b111111 @
b101 B
08
17
b10 C
1+
#1650000
0+
#1655000
b11 C
1+
#1660000
0+
#1665000
1#
18
07
b0 C
1+
#1670000
0+
#1675000
b1 C
1+
#1680000
0+
#1685000
0#
b1111111 A
b1111111 @
b110 B
08
17
b10 C
1+
#1690000
0+
#1695000
b11 C
1+
#1700000
0+
#1705000
1#
18
07
b0 C
1+
#1710000
0+
#1715000
b1 C
1+
#1720000
0+
#1725000
0#
b11111111 A
b11111111 @
b111 B
08
17
b10 C
1+
#1730000
0+
#1735000
b11 C
1+
#1740000
0+
#1745000
1#
18
07
b0 C
1+
#1750000
0+
#1755000
b1 C
1+
#1760000
0+
#1765000
0#
b111111111 A
b111111111 @
b1000 B
08
17
b10 C
1+
#1770000
0+
#1775000
b11 C
1+
#1780000
0+
#1785000
1#
18
07
b0 C
1+
#1790000
0+
#1795000
b1 C
1+
#1800000
0+
#1805000
0#
b1111111111 A
b1111111111 @
b1001 B
08
17
b10 C
1+
#1810000
0+
#1815000
b11 C
1+
#1820000
0+
#1825000
1#
18
07
b0 C
1+
#1830000
0+
#1835000
b1 C
1+
#1840000
0+
#1845000
0#
b11111111111 A
b11111111111 @
b1010 B
08
17
b10 C
1+
#1850000
0+
#1855000
b11 C
1+
#1860000
0+
#1865000
1#
18
07
b0 C
1+
#1870000
0+
#1875000
b1 C
1+
#1880000
0+
#1885000
0#
b111111111111 A
b111111111111 @
b1011 B
08
17
b10 C
1+
#1890000
0+
#1895000
b11 C
1+
#1900000
0+
#1905000
1#
18
07
b0 C
1+
#1910000
0+
#1915000
b1 C
1+
#1920000
0+
#1925000
0#
b1111111111111 A
b1111111111111 @
b1100 B
08
17
b10 C
1+
#1930000
0+
#1935000
b11 C
1+
#1940000
0+
#1945000
1#
18
07
b0 C
1+
#1950000
0+
#1955000
b1 C
1+
#1960000
0+
#1965000
0#
b11111111111111 A
b11111111111111 @
b1101 B
08
17
b10 C
1+
#1970000
0+
#1975000
b11 C
1+
#1980000
0+
#1985000
1#
18
07
b0 C
1+
#1990000
0+
#1995000
b1 C
1+
#2000000
0+
#2005000
0#
b111111111111111 A
b111111111111111 @
b1110 B
08
17
b10 C
1+
#2010000
0+
#2015000
b11 C
1+
#2020000
0+
#2025000
1#
18
07
b0 C
1+
#2030000
0+
#2035000
b1 C
1+
#2040000
0+
#2045000
0#
b1111111111111111 A
b1111111111111111 @
b1111 B
08
17
b10 C
1+
#2050000
0+
#2055000
b11 C
1+
#2060000
0+
#2065000
1#
18
07
b0 C
1+
#2070000
0+
#2075000
b1 C
1+
#2080000
0+
#2085000
0#
b11111111111111111 A
b11111111111111111 @
b10000 B
08
17
b10 C
1+
#2090000
0+
#2095000
b11 C
1+
#2100000
0+
#2105000
1#
18
07
b0 C
1+
#2110000
0+
#2115000
b1 C
1+
#2120000
0+
#2125000
0#
b111111111111111111 A
b111111111111111111 @
b10001 B
08
17
b10 C
1+
#2130000
0+
#2135000
b11 C
1+
#2140000
0+
#2145000
1#
18
07
b0 C
1+
#2150000
0+
#2155000
b1 C
1+
#2160000
0+
#2165000
0#
b1111111111111111111 A
b1111111111111111111 @
b10010 B
08
17
b10 C
1+
#2170000
0+
#2175000
b11 C
1+
#2180000
0+
#2185000
1#
18
07
b0 C
1+
#2190000
0+
#2195000
b1 C
1+
#2200000
0+
#2205000
0#
b11111111111111111111 A
b11111111111111111111 @
b10011 B
08
17
b10 C
1+
#2210000
0+
#2215000
b11 C
1+
#2220000
0+
#2225000
1#
18
07
b0 C
1+
#2230000
0+
#2235000
b1 C
1+
#2240000
0+
#2245000
0#
b111111111111111111111 A
b111111111111111111111 @
b10100 B
08
17
b10 C
1+
#2250000
0+
#2255000
b11 C
1+
#2260000
0+
#2265000
1#
18
07
b0 C
1+
#2270000
0+
#2275000
b1 C
1+
#2280000
0+
#2285000
0#
b1111111111111111111111 A
b1111111111111111111111 @
b10101 B
08
17
b10 C
1+
#2290000
0+
#2295000
b11 C
1+
#2300000
0+
#2305000
1#
18
07
b0 C
1+
#2310000
0+
#2315000
b1 C
1+
#2320000
0+
#2325000
0#
b11111111111111111111111 A
b11111111111111111111111 @
b10110 B
08
17
b10 C
1+
#2330000
0+
#2335000
b11 C
1+
#2340000
0+
#2345000
1#
18
07
b0 C
1+
#2350000
0+
#2355000
b1 C
1+
#2360000
0+
#2365000
0#
b111111111111111111111111 A
b111111111111111111111111 @
b10111 B
08
17
b10 C
1+
#2370000
0+
#2375000
b11 C
1+
#2380000
0+
#2385000
1#
18
07
b0 C
1+
#2390000
0+
#2395000
b1 C
1+
#2400000
0+
#2405000
0#
b1111111111111111111111111 A
b1111111111111111111111111 @
b11000 B
08
17
b10 C
1+
#2410000
0+
#2415000
b11 C
1+
#2420000
0+
#2425000
1#
18
07
b0 C
1+
#2430000
0+
#2435000
b1 C
1+
#2440000
0+
#2445000
0#
b11111111111111111111111111 A
b11111111111111111111111111 @
b11001 B
08
17
b10 C
1+
#2450000
0+
#2455000
b11 C
1+
#2460000
0+
#2465000
1#
18
07
b0 C
1+
#2470000
0+
#2475000
b1 C
1+
#2480000
0+
#2485000
0#
b111111111111111111111111111 A
b111111111111111111111111111 @
b11010 B
08
17
b10 C
1+
#2490000
0+
#2495000
b11 C
1+
#2500000
0+
#2505000
1#
18
07
b0 C
1+
#2510000
0+
#2515000
b1 C
1+
#2520000
0+
#2525000
0#
b1111111111111111111111111111 A
b1111111111111111111111111111 @
b11011 B
08
17
b10 C
1+
#2530000
0+
#2535000
b11 C
1+
#2540000
0+
#2545000
1#
18
07
b0 C
1+
#2550000
0+
#2555000
b1 C
1+
#2560000
0+
#2565000
0#
b11111111111111111111111111111 A
b11111111111111111111111111111 @
b11100 B
08
17
b10 C
1+
#2570000
0+
#2575000
b11 C
1+
#2580000
0+
#2585000
1#
18
07
b0 C
1+
#2590000
0+
#2595000
b1 C
1+
#2600000
0+
#2605000
0#
b111111111111111111111111111111 A
b111111111111111111111111111111 @
b11101 B
08
17
b10 C
1+
#2610000
0+
#2615000
b11 C
1+
#2620000
0+
#2625000
1#
18
07
b0 C
1+
#2630000
0+
#2635000
b1 C
1+
#2640000
0+
#2645000
0#
b1111111111111111111111111111111 A
b1111111111111111111111111111111 @
b11110 B
08
17
b10 C
1+
#2650000
0+
#2655000
b11 C
1+
#2660000
0+
#2665000
1#
18
07
b0 C
1+
#2670000
0+
#2675000
b1 C
1+
#2680000
0+
#2685000
0#
b11111111111111111111111111111111 A
b11111111111111111111111111111111 @
b11111 B
08
17
b10 C
1+
#2690000
0+
